Metadata-Version: 2.1
Name: rasa-gen
Version: 0.0.3
Summary: Rasa train data generator
Home-page: https://github.com/SchweitzerGAO/rasa-train-generator
Author: Charles Gao
Author-email: charlesgao2101024@gmail.com
License: Apache License 2.0
Keywords: Rasa chatbot,Rasa,pip
Platform: any
License-File: LICENSE
